{"0": "affirm", "1": "area", "2": "bot_challenge", "3": "broadcasting", "4": "combined", "5": "contract", "6": "cost", "7": "count", "8": "cultivation", "9": "days", "10": "deny", "11": "dry_sowing", "12": "fertilizer", "13": "fertilizer_brand", "14": "fertilizer_name", "15": "fertilizers", "16": "flooding", "17": "fungicide", "18": "fungicide_brand", "19": "fungicide_name", "20": "goodbye", "21": "greet", "22": "herbicide", "23": "herbicide_name", "24": "hour", "25": "interval_fertilizer", "26": "irrigation_method", "27": "irrigation_source", "28": "labour_cost", "29": "labour_count", "30": "lime", "31": "machanized", "32": "machinary_brand", "33": "machinary_type", "34": "manual", "35": "manure", "36": "manure_brand", "37": "manure_name", "38": "method_seeding", "39": "micronutrient_brand", "40": "micronutrient_name", "41": "micronutrients", "42": "mood_great", "43": "mood_unhappy", "44": "open_field", "45": "other", "46": "pesticide", "47": "pesticide_brand", "48": "pesticide_name", "49": "planting", "50": "precision", "51": "provide_details", "52": "provide_email", "53": "provide_name", "54": "pumping", "55": "seed_variety", "56": "seedsfrom", "57": "service_provider", "58": "sheet", "59": "show_all_data", "60": "sowing", "61": "total_cost", "62": "tray_seeding", "63": "vendor_name", "64": "vendor_number", "65": "weight", "66": "weight_seed", "67": "wet_sowing"}